LICENSE
MANIFEST.in
README.md
setup.cfg
setup.py
django_mysql_ssl.egg-info/PKG-INFO
django_mysql_ssl.egg-info/SOURCES.txt
django_mysql_ssl.egg-info/dependency_links.txt
django_mysql_ssl.egg-info/top_level.txt
django_mysql_ssl.egg-info/zip-safe
mysql_ssl/__init__.py
mysql_ssl/backends/__init__.py
mysql_ssl/backends/mysql/__init__.py
mysql_ssl/backends/mysql/client.py
mysql_ssl/management/__init__.py
mysql_ssl/management/commands/__init__.py
mysql_ssl/management/commands/dbshell_ssl.py