Metadata-Version: 1.1
Name: django-mysql-ssl
Version: 0.0.1
Summary: Backport dbshell support for ssl mysql connections in Django < 1.8
Home-page: http://github.com/cfpb/django-mysql-ssl
Author: CFPB
Author-email: tech@cfpb.gov
License: Public Domain
Platform: UNKNOWN
Classifier: Development Status :: 2 - Pre-Alpha
Classifier: Framework :: Django
Classifier: Intended Audience :: Developers
Classifier: License :: Public Domain
Classifier: Operating System :: OS Independent
Classifier: Programming Language :: Python
Classifier: Programming Language :: Python :: 2.6
Classifier: Programming Language :: Python :: 2.7
Classifier: Topic :: Internet :: WWW/HTTP :: Dynamic Content
Classifier: Topic :: Software Development :: Libraries :: Python Modules
